saucelabs_visual/__init__.py
saucelabs_visual/client.py
saucelabs_visual/regions.py
saucelabs_visual/typing.py
saucelabs_visual/utils.py
saucelabs_visual/frameworks/__init__.py
saucelabs_visual/frameworks/robot.py
saucelabs_visual-0.7.1.dist-info/METADATA
saucelabs_visual-0.7.1.dist-info/WHEEL
saucelabs_visual-0.7.1.dist-info/RECORD
