Metadata-Version: 2.4
Name: saucelabs_visual
Version: 0.7.1
Summary: Python bindings for Sauce Labs Visual
Project-URL: Homepage, https://github.com/saucelabs/visual-sdks/tree/main/visual-python
Project-URL: Issues, https://github.com/saucelabs/visual-sdks/issues
Requires-Dist: gql
Requires-Dist: requests
Requires-Dist: requests-toolbelt
Requires-Dist: tabulate
